sqlt/__init__.py
sqlt/db.py
sqlt/sqlt.py
sqlt-0.0.6.dist-info/METADATA
sqlt-0.0.6.dist-info/WHEEL
sqlt-0.0.6.dist-info/top_level.txt
sqlt-0.0.6.dist-info/RECORD
