Metadata-Version: 2.1
Name: sqlt
Version: 0.0.6
Summary: A small sqlite wrapper + tools
Home-page: UNKNOWN
Author: biscotte
License: UNKNOWN
Platform: any
Classifier: Programming Language :: Python :: 2
Classifier: Programming Language :: Python :: 3
Classifier: License :: OSI Approved :: MIT License
Classifier: Operating System :: OS Independent
